README.md
setup.py
delog/__init__.py
delog/caller.py
delog/constants.py
delog/delog.py
delog/graphql.py
delog/utilities.py
delog.egg-info/PKG-INFO
delog.egg-info/SOURCES.txt
delog.egg-info/dependency_links.txt
delog.egg-info/requires.txt
delog.egg-info/top_level.txt