Metadata-Version: 2.1
Name: delog
Version: 0.0.8
Summary: client for centralized logging on a delog server
Home-page: https://github.com/plurid/delog
Author: ly3xqhl8g9
Author-email: ly3xqhl8g9@plurid.com
License: UNKNOWN
Platform: UNKNOWN
Classifier: Programming Language :: Python :: 3
Classifier: License :: OSI Approved :: MIT License
Classifier: Operating System :: OS Independent
Requires-Python: >=3.6
